CHANGELOG.md
CHANGES.md
CONTRIBUTING.md
Dockerfile
LICENSE
MANIFEST.in
ROADMAP.md
SWARM.md
requirements-dev.txt
requirements.txt
setup.py
tox.ini
compose/__init__.py
compose/const.py
compose/container.py
compose/parallel.py
compose/progress_stream.py
compose/project.py
compose/service.py
compose/state.py
compose/utils.py
compose/cli/__init__.py
compose/cli/colors.py
compose/cli/command.py
compose/cli/docker_client.py
compose/cli/docopt_command.py
compose/cli/errors.py
compose/cli/formatter.py
compose/cli/log_printer.py
compose/cli/main.py
compose/cli/multiplexer.py
compose/cli/utils.py
compose/cli/verbose_proxy.py
compose/config/__init__.py
compose/config/config.py
compose/config/errors.py
compose/config/fields_schema.json
compose/config/interpolation.py
compose/config/service_schema.json
compose/config/sort_services.py
compose/config/types.py
compose/config/validation.py
contrib/completion/bash/docker-compose
contrib/completion/zsh/_docker-compose
docker_compose_xu.egg-info/PKG-INFO
docker_compose_xu.egg-info/SOURCES.txt
docker_compose_xu.egg-info/dependency_links.txt
docker_compose_xu.egg-info/entry_points.txt
docker_compose_xu.egg-info/requires.txt
docker_compose_xu.egg-info/top_level.txt
tests/__init__.py
tests/acceptance/__init__.py
tests/acceptance/cli_test.py
tests/fixtures/UpperCaseDir/docker-compose.yml
tests/fixtures/build-ctx/Dockerfile
tests/fixtures/build-path/docker-compose.yml
tests/fixtures/commands-composefile/docker-compose.yml
tests/fixtures/dockerfile-with-volume/Dockerfile
tests/fixtures/dockerfile_with_entrypoint/.coverage.snow-young.local.25404.906199
tests/fixtures/dockerfile_with_entrypoint/.coverage.snow-young.local.26292.610580
tests/fixtures/dockerfile_with_entrypoint/.coverage.snow-young.local.28791.846765
tests/fixtures/dockerfile_with_entrypoint/.coverage.snow-young.local.31100.440305
tests/fixtures/dockerfile_with_entrypoint/.coverage.snow-young.local.318.707076
tests/fixtures/dockerfile_with_entrypoint/.coverage.snow-young.local.31973.016845
tests/fixtures/dockerfile_with_entrypoint/.coverage.snow-young.local.32314.568442
tests/fixtures/dockerfile_with_entrypoint/.coverage.snow-young.local.40681.533370
